lucyballs/__init__.py
lucyballs/lucy.py
lucyballs-0.0.1.dist-info/METADATA
lucyballs-0.0.1.dist-info/RECORD
lucyballs-0.0.1.dist-info/WHEEL
lucyballs-0.0.1.dist-info/top_level.txt
