Metadata-Version: 2.1
Name: lucyballs
Version: 0.0.1
Summary: the most lucy package out there
Home-page: https://github.com/pypa/sampleproject
Author: Lucas Selfslagh
Author-email: author@example.com
License: UNKNOWN
Platform: UNKNOWN
Classifier: Programming Language :: Python :: 3
Classifier: License :: OSI Approved :: MIT License
Classifier: Operating System :: OS Independent
